giternity.py
giternity-0.6.dist-info/LICENSE.txt
giternity-0.6.dist-info/METADATA
giternity-0.6.dist-info/WHEEL
giternity-0.6.dist-info/entry_points.txt
giternity-0.6.dist-info/top_level.txt
giternity-0.6.dist-info/RECORD
